LICENSE
README.md
pyproject.toml
libKSG/__init__.py
libKSG/libKSG.py
libKSG.egg-info/PKG-INFO
libKSG.egg-info/SOURCES.txt
libKSG.egg-info/dependency_links.txt
libKSG.egg-info/requires.txt
libKSG.egg-info/top_level.txt
libKSG/src/kdtree.c
libKSG/src/ksg.c
libKSG/src/ksg.h
libKSG/src/unique.c
test/test.py