Metadata-Version: 2.2
Name: libKSG
Version: 0.0.1
Summary: Compute Mutual Information using the KSG estimator (1st algo)
Author-email: HaoRan Chang <haoran.chang@mail.mcgill.ca>
License:                     GNU GENERAL PUBLIC LICENSE
Project-URL: Homepage, https://github.com/LelouchLamperougeVI/libKSG
Project-URL: Issues, https://github.com/LelouchLamperougeVI/libKSG/issues
Classifier: Development Status :: 4 - Beta
Classifier: Programming Language :: Python :: 3
Classifier: Operating System :: POSIX :: Linux
Requires-Python: >=3.11
License-File: LICENSE
Requires-Dist: numpy>=1.26
